Metadata-Version: 2.1
Name: rhasspy-hermes-app
Version: 1.1.2
Summary: UNKNOWN
Home-page: https://github.com/rhasspy/rhasspy-hermes-app
Author: Koen Vervloesem
Author-email: koen@vervloesem.eu
License: UNKNOWN
Platform: UNKNOWN
Classifier: Development Status :: 3 - Alpha
Classifier: Intended Audience :: Developers
Classifier: License :: OSI Approved :: MIT License
Classifier: Programming Language :: Python :: 3
Classifier: Programming Language :: Python :: 3.7
Classifier: Programming Language :: Python :: 3.8
Classifier: Topic :: Software Development :: Libraries
Requires-Python: >=3.7
